qr_payment_slip/__init__.py
qr_payment_slip/address.py
qr_payment_slip/bill.py
qr_payment_slip/errors.py
qr_payment_slip/printer.py
tests/__init__.py
tests/test_address.py
tests/test_integration.py
tests/test_printer.py
tests/test_qrbill.py
QR_payment_slip-0.1.0.dist-info/LICENSE.TXT
QR_payment_slip-0.1.0.dist-info/METADATA
QR_payment_slip-0.1.0.dist-info/WHEEL
QR_payment_slip-0.1.0.dist-info/top_level.txt
QR_payment_slip-0.1.0.dist-info/RECORD
