Metadata-Version: 2.1
Name: QR-payment-slip
Version: 0.1.0
Summary: QR payment slip generator for Switzerland and Lichtenstein
Home-page: UNKNOWN
Author: Rafael S. Müller
Author-email: rafa.molitoris@gmail.com
License: UNKNOWN
Project-URL: Source Code, https://github.com/molitoris/qr_payment_slip
Keywords: QR payment slip bill swiss payment standard
Platform: UNKNOWN
Classifier: Intended Audience :: Developers
Classifier: License :: OSI Approved :: GNU Lesser General Public License v3 (LGPLv3)
Classifier: Operating System :: OS Independent
Classifier: Programming Language :: Python :: 3.7
Requires-Dist: svgwrite (~=1.4)
Requires-Dist: qrcode (~=6.1)
Requires-Dist: python-stdnum (~=1.13)
Requires-Dist: iso3166 (~=1.0.1)
Requires-Dist: setuptools (~=49.2.0)
